us/__init__.py
us/statesandlocalities.py
us/unitedstatesofamerica.py
us/cli/__init__.py
us/cli/states.py
uslocaljuris_bah-0.0.5.dist-info/METADATA
uslocaljuris_bah-0.0.5.dist-info/WHEEL
uslocaljuris_bah-0.0.5.dist-info/licenses/LICENSE.rtf
uslocaljuris_bah-0.0.5.dist-info/RECORD
