Metadata-Version: 2.1
Name: USLocalJuris_BAH
Version: 0.0.5
Summary: A small example package
Project-URL: Homepage, https://github.com/BryanAHuang/USLocalJuris_BAH
Project-URL: Bug Tracker, https://github.com/BryanAHuang/USLocalJuris_BAH/issues
Author-email: BAH <author@example.com>
License-File: LICENSE.rtf
Classifier: License :: OSI Approved :: MIT License
Classifier: Operating System :: OS Independent
Classifier: Programming Language :: Python :: 3
Requires-Python: >=3.7
